<?xml version = '1.0' encoding = 'UTF-8'?>
<Relation class="oracle.dbtools.crest.model.design.logical.Relation" name="Relation_17" directorySegmentName="seg_0" id="7884B6F7-8D25-2227-E31D-B46170667178">
<createdBy>krsti</createdBy>
<createdTime>2024-03-15 18:36:22 UTC</createdTime>
<ownerDesignName>web_trgovina_rk</ownerDesignName>
<shouldEngineer>false</shouldEngineer>
<engineerTo>
<item key="3800A34D-0927-C4DC-7F6E-2F76D88BE5A3" value="false"/>
</engineerTo>
<sourcePk>2FC89291-8115-8A15-C2BA-5E6E5B758C3A</sourcePk>
<identifying>false</identifying>
<optionalSource>false</optionalSource>
<optionalTarget>false</optionalTarget>
<sourceCardinality>1</sourceCardinality>
<sourceEntity>3523AA2C-C765-5886-8733-1258DCBA419D</sourceEntity>
<targetCardinalityString>*</targetCardinalityString>
<targetEntity>050F15CC-E9C4-5800-F27F-5FA3E88E5643</targetEntity>
<transferable>true</transferable>
<deleteRule>NO ACTION</deleteRule>
</Relation>